django_gem/__init__.py
django_gem/apps.py
django_gem/constants.py
django_gem/context/__init__.py
django_gem/context/cutting_always_eager.py
django_gem/context/override_anvil.py
django_gem/context/override_cutting_mode.py
django_gem/context/override_gem_setting.py
django_gem/core.py
django_gem/cutters/__init__.py
django_gem/cutters/base.py
django_gem/decorators/__init__.py
django_gem/decorators/conditional_transaction.py
django_gem/decorators/context.py
django_gem/decorators/cutters.py
django_gem/decorators/exceptions.py
django_gem/decorators/models.py
django_gem/entities/__init__.py
django_gem/entities/context.py
django_gem/entities/models.py
django_gem/entities/registry.py
django_gem/entities/source.py
django_gem/exceptions.py
django_gem/logger.py
django_gem/management/__init__.py
django_gem/management/commands/__init__.py
django_gem/management/commands/cutmodel.py
django_gem/management/commands/cutqueryset.py
django_gem/management/commands/gemmakemigrations.py
django_gem/management/commands/gemmigrate.py
django_gem/middlewares/__init__.py
django_gem/middlewares/gem_context_middleware.py
django_gem/migrations/0001_initial.py
django_gem/migrations/__init__.py
django_gem/models/__init__.py
django_gem/models/base.py
django_gem/models/gem_log_entry.py
django_gem/models/managers/__init__.py
django_gem/models/managers/gem_log_entry_manager.py
django_gem/models/mixins.py
django_gem/overrides/__init__.py
django_gem/overrides/delete.py
django_gem/overrides/m2m_changed.py
django_gem/overrides/save.py
django_gem/overrides/utils.py
django_gem/tasks/__init__.py
django_gem/tasks/cut_content_type.py
django_gem/tasks/cut_models.py
django_gem/tasks/cut_queryset.py
django_gem/toolkit/__init__.py
django_gem/toolkit/anvils/__init__.py
django_gem/toolkit/anvils/base.py
django_gem/toolkit/anvils/celery.py
django_gem/toolkit/anvils/eager.py
django_gem/toolkit/chest.py
django_gem/toolkit/forge.py
django_gem/toolkit/gem_migration/__init__.py
django_gem/toolkit/gem_migration/collector.py
django_gem-1.5.4.dist-info/LICENSE
django_gem-1.5.4.dist-info/METADATA
django_gem-1.5.4.dist-info/WHEEL
django_gem-1.5.4.dist-info/RECORD
