Metadata-Version: 2.1
Name: django-gem
Version: 1.5.4
Summary: Distrubited calculations for Django models
License: MIT
Author: Artur Veres
Author-email: artur8118@gmail.com
Requires-Python: >=3.10,<3.13
Classifier: License :: OSI Approved :: MIT License
Classifier: Programming Language :: Python :: 3
Classifier: Programming Language :: Python :: 3.10
Classifier: Programming Language :: Python :: 3.11
Classifier: Programming Language :: Python :: 3.12
Requires-Dist: celery (>=5.4.0,<6.0.0)
Requires-Dist: django (>=3.0.0,<6.0.0)
Requires-Dist: django-crum (>=0.7.9,<0.8.0)
Requires-Dist: django-dirtyfields (>=1.9.3,<2.0.0)
